{
    "market_type": "futures",
    "user": "binance_tedy",
    "symbol": "DOGEUSDT",
    "latency_simulation_ms": 1000,
    "starting_balance": 1000.0,
    "start_date": "2020-01-01",
    "end_date": "2023-12-18",
    "slim_analysis": true,
    "base_dir": "/storage/tedy/passivbot/configs/live/PBSO/BT_UNIFORMISED/bt_2020-01-01_2023-12-18_1000_1/strat_ab1790c54d2fcf8573ff7379d83f4998/",
    "ohlcv": true,
    "adg_n_subdivisions": 10,
    "enable_interactive_plot": false,
    "plot_theme": "light",
    "plot_candles_interval": "1m",
    "symbols": [
        "DOGEUSDT"
    ],
    "spot": false,
    "exchange": "binance",
    "session_name": "2020-01-01_2023-12-18",
    "caches_dirpath": "/storage/tedy/passivbot/configs/live/PBSO/BT_UNIFORMISED/bt_2020-01-01_2023-12-18_1000_1/strat_ab1790c54d2fcf8573ff7379d83f4998/binance/DOGEUSDT/caches/",
    "plots_dirpath": "/storage/tedy/passivbot/configs/live/PBSO/BT_UNIFORMISED/bt_2020-01-01_2023-12-18_1000_1/strat_ab1790c54d2fcf8573ff7379d83f4998/binance/DOGEUSDT/plots/2024-01-07T151542/",
    "c_mult": 1.0,
    "hedge_mode": true,
    "inverse": false,
    "maker_fee": 0.0002,
    "min_cost": 5.0,
    "min_qty": 1.0,
    "price_step": 1e-05,
    "qty_step": 1.0,
    "taker_fee": 0.0004,
    "n_parts": 0,
    "config_name": "clock_0days",
    "long": {
        "backwards_tp": true,
        "delay_between_fills_minutes_close": 641.2076201234992,
        "delay_between_fills_minutes_entry": 1347.508706249823,
        "delay_weight_close": 73.34009606440834,
        "delay_weight_entry": 38.59204628001405,
        "ema_dist_close": -0.023246293388293343,
        "ema_dist_entry": 0.002477021337675177,
        "ema_span_0": 261.3839616265429,
        "ema_span_1": 30.391479661022007,
        "enabled": true,
        "markup_range": 0.05989457572063947,
        "min_markup": 0.0018352474850221515,
        "n_close_orders": 7,
        "qty_pct_close": 0.046453395944339955,
        "qty_pct_entry": 0.01,
        "wallet_exposure_limit": 1,
        "we_multiplier_close": 90.92165701022176,
        "we_multiplier_entry": 95.01329471586385
    },
    "short": {
        "backwards_tp": true,
        "delay_between_fills_minutes_close": 1251.515828174044,
        "delay_between_fills_minutes_entry": 1018.1472201346212,
        "delay_weight_close": 66.12821669023366,
        "delay_weight_entry": 24.19747365170568,
        "ema_dist_close": 0.003993172156863785,
        "ema_dist_entry": 0.0012323094836629983,
        "ema_span_0": 1292.0273329340998,
        "ema_span_1": 79.46997260037871,
        "enabled": false,
        "markup_range": 0.004934397866657937,
        "min_markup": 0.003662376497591767,
        "n_close_orders": 8,
        "qty_pct_close": 0.04364125845774393,
        "qty_pct_entry": 0.010015758582063345,
        "wallet_exposure_limit": 1,
        "we_multiplier_close": 0.004883990966962433,
        "we_multiplier_entry": 68.07026112341265
    },
    "disable_plotting": false,
    "passivbot_mode": "clock",
    "n_days": 1255.6,
    "result": {
        "adg_long": 0.0025359010447103536,
        "adg_per_exposure_long": 0.0025359010447103536,
        "adg_per_exposure_short": 0.0,
        "adg_short": 0.0,
        "adg_weighted_long": 0.0006197986549921098,
        "adg_weighted_per_exposure_long": 0.0006197986549921098,
        "adg_weighted_per_exposure_short": 0.0,
        "adg_weighted_short": 0.0,
        "avg_fills_per_day_long": 12.504550364278023,
        "avg_fills_per_day_short": 0.0,
        "closest_bkr_long": 0.9998832701576917,
        "closest_bkr_short": 1.0,
        "drawdown_1pct_worst_mean_long": 0.08824974686235419,
        "drawdown_1pct_worst_mean_short": -0.0,
        "drawdown_max_long": 0.2719826433397744,
        "drawdown_max_short": -0.0,
        "eqbal_ratio_mean_long": 0.999811544028025,
        "eqbal_ratio_mean_of_10_worst_long": 0.8308146183724704,
        "eqbal_ratio_mean_of_10_worst_short": 1.0,
        "eqbal_ratio_mean_short": 1.0,
        "eqbal_ratio_min_long": 0.7268325393817832,
        "eqbal_ratio_min_short": NaN,
        "eqbal_ratio_std_long": 0.004053722331694287,
        "eqbal_ratio_std_short": 0.0,
        "equity_balance_ratio_mean_long": 0.999811544028025,
        "equity_balance_ratio_mean_short": 1.0,
        "equity_balance_ratio_std_long": 0.004053722331694287,
        "equity_balance_ratio_std_short": 0.0,
        "exchange": "binance",
        "exposure_ratios_mean_long": 0.014489672909538334,
        "exposure_ratios_mean_short": 0.0,
        "fee_sum_long": -1080.9858685338002,
        "fee_sum_short": 0,
        "final_balance_long": 24049.277450466347,
        "final_balance_short": 1000.0,
        "final_equity_long": 24045.293070466345,
        "final_equity_short": 1000.0,
        "gain_long": 23.049277450466345,
        "gain_short": 0.0,
        "hrs_stuck_avg_long": 1.919384288747346,
        "hrs_stuck_avg_short": NaN,
        "hrs_stuck_max_long": 81.91666666666667,
        "hrs_stuck_max_short": NaN,
        "loss_profit_ratio_long": 0.20388256941345623,
        "loss_profit_ratio_short": 1.0,
        "loss_sum_long": -6179.666337008031,
        "loss_sum_short": 0,
        "n_closes_long": 6518,
        "n_closes_short": 0,
        "n_days": 1255.6229166666667,
        "n_entries_long": 9183,
        "n_entries_short": 0,
        "n_fills_long": 15701,
        "n_fills_short": 0,
        "n_ientries_long": 0,
        "n_ientries_short": 0,
        "n_normal_closes_long": 432,
        "n_normal_closes_short": 0,
        "n_rentries_long": 0,
        "n_rentries_short": 0,
        "n_unstuck_closes_long": 6086,
        "n_unstuck_closes_short": 0,
        "n_unstuck_entries_long": 9183,
        "n_unstuck_entries_short": 0,
        "net_pnl_plus_fees_long": 23049.277450466194,
        "net_pnl_plus_fees_short": 0,
        "pa_distance_1pct_worst_mean_long": 0.03923284261105271,
        "pa_distance_1pct_worst_mean_short": 100.0,
        "pa_distance_max_long": 0.3758007726268934,
        "pa_distance_max_short": 100.0,
        "pa_distance_mean_long": 0.0058758459924291235,
        "pa_distance_mean_short": 100.0,
        "pa_distance_std_long": 0.00806513420175053,
        "pa_distance_std_short": 1.0,
        "pnl_sum_long": 24130.263318999994,
        "pnl_sum_short": 0,
        "profit_sum_long": 30309.929656008026,
        "profit_sum_short": 0,
        "sharpe_ratio_long": 0.19525393086590512,
        "sharpe_ratio_short": 0.0,
        "starting_balance": 1000.0,
        "symbol": "DOGEUSDT",
        "time_at_max_exposure_long": 0.002621449429254048,
        "time_at_max_exposure_short": 0.0,
        "volume_quote_long": 5980987.283148191,
        "volume_quote_short": 0
    }
}