{
    "market_type": "futures",
    "user": "binance_tedy",
    "symbol": "TRXUSDT",
    "latency_simulation_ms": 1000,
    "starting_balance": 1000.0,
    "start_date": "2020-01-01",
    "end_date": "2023-12-18",
    "slim_analysis": true,
    "base_dir": "/storage/tedy/passivbot/configs/live/PBSO/BT_UNIFORMISED/bt_2020-01-01_2023-12-18_1000_1/strat_15e780b5bd910f91c3fafdd04fabfb62/",
    "ohlcv": true,
    "adg_n_subdivisions": 10,
    "enable_interactive_plot": false,
    "plot_theme": "light",
    "plot_candles_interval": "1m",
    "symbols": [
        "TRXUSDT"
    ],
    "spot": false,
    "exchange": "binance",
    "session_name": "2020-01-01_2023-12-18",
    "caches_dirpath": "/storage/tedy/passivbot/configs/live/PBSO/BT_UNIFORMISED/bt_2020-01-01_2023-12-18_1000_1/strat_15e780b5bd910f91c3fafdd04fabfb62/binance/TRXUSDT/caches/",
    "plots_dirpath": "/storage/tedy/passivbot/configs/live/PBSO/BT_UNIFORMISED/bt_2020-01-01_2023-12-18_1000_1/strat_15e780b5bd910f91c3fafdd04fabfb62/binance/TRXUSDT/plots/2023-12-25T165650/",
    "c_mult": 1.0,
    "hedge_mode": true,
    "inverse": false,
    "maker_fee": 0.0002,
    "min_cost": 5.0,
    "min_qty": 1.0,
    "price_step": 1e-05,
    "qty_step": 1.0,
    "taker_fee": 0.0004,
    "n_parts": 0,
    "config_name": "emas_0days",
    "long": {
        "backwards_tp": true,
        "delay_between_fills_minutes_close": 141.0504028929519,
        "delay_between_fills_minutes_entry": 485.8670392332931,
        "delay_weight_close": 61.33177741373494,
        "delay_weight_entry": 28.406582498838727,
        "ema_dist_close": -0.05571541695143538,
        "ema_dist_entry": -0.4741102280251457,
        "ema_span_0": 993.4300606666984,
        "ema_span_1": 1421.2606699869693,
        "enabled": true,
        "markup_range": 0.026639815375102478,
        "min_markup": 0.014727096342102192,
        "n_close_orders": 5,
        "qty_pct_close": 0.0031155084375018723,
        "qty_pct_entry": 0.00788114049698354,
        "wallet_exposure_limit": 1,
        "we_multiplier_close": 52.77500113777817,
        "we_multiplier_entry": 70.47596759261327
    },
    "short": {
        "backwards_tp": true,
        "delay_between_fills_minutes_close": 38.262355828000324,
        "delay_between_fills_minutes_entry": 284.69785258084164,
        "delay_weight_close": 21.201831425772966,
        "delay_weight_entry": 10.723875530650318,
        "ema_dist_close": 0.01141126197920894,
        "ema_dist_entry": 0.01077434598301382,
        "ema_span_0": 1129.70993002142,
        "ema_span_1": 3106.289737466466,
        "enabled": false,
        "markup_range": 0.018665107790339145,
        "min_markup": 0.007192858570885791,
        "n_close_orders": 3,
        "qty_pct_close": 0.012137420286897713,
        "qty_pct_entry": 0.03869806789481021,
        "wallet_exposure_limit": 1,
        "we_multiplier_close": 111.54341421720126,
        "we_multiplier_entry": 145.31527430825588
    },
    "disable_plotting": false,
    "passivbot_mode": "clock",
    "n_days": 1432.7,
    "result": {
        "adg_long": 0.0004526920589384975,
        "adg_per_exposure_long": 0.0004526920589384975,
        "adg_per_exposure_short": 0.0,
        "adg_short": 0.0,
        "adg_weighted_long": 9.088528349713299e-05,
        "adg_weighted_per_exposure_long": 9.088528349713299e-05,
        "adg_weighted_per_exposure_short": 0.0,
        "adg_weighted_short": 0.0,
        "avg_fills_per_day_long": 23.81512259625638,
        "avg_fills_per_day_short": 0.0,
        "closest_bkr_long": 0.9999170833422,
        "closest_bkr_short": 1.0,
        "drawdown_1pct_worst_mean_long": 0.21408087194738182,
        "drawdown_1pct_worst_mean_short": -0.0,
        "drawdown_max_long": 0.43527538935783755,
        "drawdown_max_short": -0.0,
        "eqbal_ratio_mean_long": 0.9992287054287852,
        "eqbal_ratio_mean_of_10_worst_long": 0.6811049115864402,
        "eqbal_ratio_mean_of_10_worst_short": 1.0,
        "eqbal_ratio_mean_short": 1.0,
        "eqbal_ratio_min_long": 0.5650137683958392,
        "eqbal_ratio_min_short": NaN,
        "eqbal_ratio_std_long": 0.010198490553028499,
        "eqbal_ratio_std_short": 0.0,
        "equity_balance_ratio_mean_long": 0.9992287054287852,
        "equity_balance_ratio_mean_short": 1.0,
        "equity_balance_ratio_std_long": 0.010198490553028499,
        "equity_balance_ratio_std_short": 0.0,
        "exchange": "binance",
        "exposure_ratios_mean_long": 0.02408110653063052,
        "exposure_ratios_mean_short": 0.0,
        "fee_sum_long": -110.94546738600002,
        "fee_sum_short": 0,
        "final_balance_long": 1912.492862614002,
        "final_balance_short": 1000.0,
        "final_equity_long": 1912.4295026140019,
        "final_equity_short": 1000.0,
        "gain_long": 0.9124928626140021,
        "gain_short": 0.0,
        "hrs_stuck_avg_long": 1.0077627645231255,
        "hrs_stuck_avg_short": NaN,
        "hrs_stuck_max_long": 24.15,
        "hrs_stuck_max_short": NaN,
        "loss_profit_ratio_long": 0.6198370059023458,
        "loss_profit_ratio_short": 1.0,
        "loss_sum_long": -1668.6657040320597,
        "loss_sum_short": 0,
        "n_closes_long": 21231,
        "n_closes_short": 0,
        "n_days": 1432.6611111111113,
        "n_entries_long": 12888,
        "n_entries_short": 0,
        "n_fills_long": 34119,
        "n_fills_short": 0,
        "n_ientries_long": 0,
        "n_ientries_short": 0,
        "n_normal_closes_long": 202,
        "n_normal_closes_short": 0,
        "n_rentries_long": 0,
        "n_rentries_short": 0,
        "n_unstuck_closes_long": 21029,
        "n_unstuck_closes_short": 0,
        "n_unstuck_entries_long": 12888,
        "n_unstuck_entries_short": 0,
        "net_pnl_plus_fees_long": 912.4928626140018,
        "net_pnl_plus_fees_short": 0,
        "pa_distance_1pct_worst_mean_long": 0.09127517308499941,
        "pa_distance_1pct_worst_mean_short": 100.0,
        "pa_distance_max_long": 0.7698065440221585,
        "pa_distance_max_short": 100.0,
        "pa_distance_mean_long": 0.006091548834739104,
        "pa_distance_mean_short": 100.0,
        "pa_distance_std_long": 0.014021807692841079,
        "pa_distance_std_short": 1.0,
        "pnl_sum_long": 1023.4383300000018,
        "pnl_sum_short": 0,
        "profit_sum_long": 2692.1040340320615,
        "profit_sum_short": 0,
        "sharpe_ratio_long": 0.04497523600111147,
        "sharpe_ratio_short": 0.0,
        "starting_balance": 1000.0,
        "symbol": "TRXUSDT",
        "time_at_max_exposure_long": 0.009626290533662934,
        "time_at_max_exposure_short": 0.0,
        "volume_quote_long": 1226954.1352801565,
        "volume_quote_short": 0
    }
}