{
    "market_type": "futures",
    "user": "binance_tedy",
    "symbol": "DOTUSDT",
    "latency_simulation_ms": 1000,
    "starting_balance": 1000.0,
    "start_date": "2020-01-01",
    "end_date": "2023-12-18",
    "slim_analysis": true,
    "base_dir": "/storage/tedy/passivbot/configs/live/PBSO/BT_UNIFORMISED/bt_2020-01-01_2023-12-18_1000_1/strat_93995a6bff954c75abed44752a84c7f4/",
    "ohlcv": true,
    "adg_n_subdivisions": 10,
    "enable_interactive_plot": false,
    "plot_theme": "light",
    "plot_candles_interval": "1m",
    "symbols": [
        "DOTUSDT"
    ],
    "spot": false,
    "exchange": "binance",
    "session_name": "2020-01-01_2023-12-18",
    "caches_dirpath": "/storage/tedy/passivbot/configs/live/PBSO/BT_UNIFORMISED/bt_2020-01-01_2023-12-18_1000_1/strat_93995a6bff954c75abed44752a84c7f4/binance/DOTUSDT/caches/",
    "plots_dirpath": "/storage/tedy/passivbot/configs/live/PBSO/BT_UNIFORMISED/bt_2020-01-01_2023-12-18_1000_1/strat_93995a6bff954c75abed44752a84c7f4/binance/DOTUSDT/plots/2024-01-07T123252/",
    "c_mult": 1.0,
    "hedge_mode": true,
    "inverse": false,
    "maker_fee": 0.0002,
    "min_cost": 5.0,
    "min_qty": 0.1,
    "price_step": 0.001,
    "qty_step": 0.1,
    "taker_fee": 0.0004,
    "n_parts": 0,
    "config_name": "recursive_grid_0days",
    "logging_level": 0,
    "long": {
        "auto_unstuck_delay_minutes": 0.0,
        "auto_unstuck_ema_dist": -0.008859325397219089,
        "auto_unstuck_qty_pct": 0.0,
        "auto_unstuck_wallet_exposure_threshold": 0.0438714952165182,
        "backwards_tp": true,
        "ddown_factor": 2.950295462921184,
        "ema_span_0": 1266.4028797656565,
        "ema_span_1": 1414.8828448427018,
        "enabled": true,
        "initial_eprice_ema_dist": -0.009254900081938052,
        "initial_qty_pct": 0.010653709416147423,
        "markup_range": 0.004653304902705119,
        "min_markup": 0.002277860912191983,
        "n_close_orders": 9,
        "rentry_pprice_dist": 0.03474506474709689,
        "rentry_pprice_dist_wallet_exposure_weighting": 1.3136226872787837,
        "wallet_exposure_limit": 1
    },
    "short": {
        "auto_unstuck_delay_minutes": 0.0,
        "auto_unstuck_ema_dist": 0.002844916218987555,
        "auto_unstuck_qty_pct": 0.0,
        "auto_unstuck_wallet_exposure_threshold": 0.06319385857376113,
        "backwards_tp": true,
        "ddown_factor": 1.5903552170814916,
        "ema_span_0": 1434.7163889367168,
        "ema_span_1": 772.0417485418991,
        "enabled": false,
        "initial_eprice_ema_dist": 0.004,
        "initial_qty_pct": 0.013417753439701186,
        "markup_range": 0.00747808426470418,
        "min_markup": 0.003234492633897589,
        "n_close_orders": 2,
        "rentry_pprice_dist": 0.04960211994920235,
        "rentry_pprice_dist_wallet_exposure_weighting": 0.16400666733643587,
        "wallet_exposure_limit": 1
    },
    "disable_plotting": false,
    "passivbot_mode": "recursive_grid",
    "n_days": 1212.7,
    "result": {
        "adg_long": 0.0007121803523602033,
        "adg_per_exposure_long": 0.0007121803523602033,
        "adg_per_exposure_short": 0.0,
        "adg_short": 0.0,
        "adg_weighted_long": 0.0004086451400132418,
        "adg_weighted_per_exposure_long": 0.0004086451400132418,
        "adg_weighted_per_exposure_short": 0.0,
        "adg_weighted_short": 0.0,
        "avg_fills_per_day_long": 16.887575590984056,
        "avg_fills_per_day_short": 0.0,
        "closest_bkr_long": 0.995208502890347,
        "closest_bkr_short": 1.0,
        "drawdown_1pct_worst_mean_long": 0.14454156108938296,
        "drawdown_1pct_worst_mean_short": -0.0,
        "drawdown_max_long": 0.26371681170374617,
        "drawdown_max_short": -0.0,
        "eqbal_ratio_mean_long": 0.9986864991319839,
        "eqbal_ratio_mean_of_10_worst_long": 0.8299239042468518,
        "eqbal_ratio_mean_of_10_worst_short": 1.0,
        "eqbal_ratio_mean_short": 1.0,
        "eqbal_ratio_min_long": 0.7359098268443998,
        "eqbal_ratio_min_short": NaN,
        "eqbal_ratio_std_long": 0.008696365774406929,
        "eqbal_ratio_std_short": 0.0,
        "equity_balance_ratio_mean_long": 0.9986864991319839,
        "equity_balance_ratio_mean_short": 1.0,
        "equity_balance_ratio_std_long": 0.008696365774406929,
        "equity_balance_ratio_std_short": 0.0,
        "exchange": "binance",
        "exposure_ratios_mean_long": 0.043163918194994995,
        "exposure_ratios_mean_short": 0.0,
        "fee_sum_long": -222.28989476000004,
        "fee_sum_short": 0,
        "final_balance_long": 2371.043105239895,
        "final_balance_short": 1000.0,
        "final_equity_long": 2368.614405239895,
        "final_equity_short": 1000.0,
        "gain_long": 1.3710431052398948,
        "gain_short": 0.0,
        "hrs_stuck_avg_long": 1.419869290620829,
        "hrs_stuck_avg_short": NaN,
        "hrs_stuck_max_long": 241.16666666666666,
        "hrs_stuck_max_short": NaN,
        "loss_profit_ratio_long": 0.4357885927371876,
        "loss_profit_ratio_short": 1.0,
        "loss_sum_long": -1230.6669749913112,
        "loss_sum_short": 0,
        "n_closes_long": 10038,
        "n_closes_short": 0,
        "n_days": 1212.6666666666667,
        "n_entries_long": 10441,
        "n_entries_short": 0,
        "n_fills_long": 20479,
        "n_fills_short": 0,
        "n_ientries_long": 7327,
        "n_ientries_short": 0,
        "n_normal_closes_long": 8800,
        "n_normal_closes_short": 0,
        "n_rentries_long": 1875,
        "n_rentries_short": 0,
        "n_unstuck_closes_long": 1238,
        "n_unstuck_closes_short": 0,
        "n_unstuck_entries_long": 1239,
        "n_unstuck_entries_short": 0,
        "net_pnl_plus_fees_long": 1371.0431052399877,
        "net_pnl_plus_fees_short": 0,
        "pa_distance_1pct_worst_mean_long": 0.08344548609613676,
        "pa_distance_1pct_worst_mean_short": 100.0,
        "pa_distance_max_long": 0.35878835309114904,
        "pa_distance_max_short": 100.0,
        "pa_distance_mean_long": 0.011048298969534015,
        "pa_distance_mean_short": 100.0,
        "pa_distance_std_long": 0.01278141821999284,
        "pa_distance_std_short": 1.0,
        "pnl_sum_long": 1593.3329999999878,
        "pnl_sum_short": 0,
        "profit_sum_long": 2823.999974991299,
        "profit_sum_short": 0,
        "sharpe_ratio_long": 0.08962845895749715,
        "sharpe_ratio_short": 0.0,
        "starting_balance": 1000.0,
        "symbol": "DOTUSDT",
        "time_at_max_exposure_long": 0.017591479127297714,
        "time_at_max_exposure_short": 0.0,
        "volume_quote_long": 5859227.429399521,
        "volume_quote_short": 0
    }
}