{
    "market_type": "futures",
    "user": "binance_tedy",
    "symbol": "UNIUSDT",
    "latency_simulation_ms": 1000,
    "starting_balance": 1000.0,
    "start_date": "2020-01-01",
    "end_date": "2023-12-18",
    "slim_analysis": true,
    "base_dir": "/storage/tedy/passivbot/configs/live/PBSO/BT_UNIFORMISED/bt_2020-01-01_2023-12-18_1000_1/strat_1c4fcf41f6a3813cd46d5a6e27490857/",
    "ohlcv": true,
    "adg_n_subdivisions": 10,
    "enable_interactive_plot": false,
    "plot_theme": "light",
    "plot_candles_interval": "1m",
    "symbols": [
        "UNIUSDT"
    ],
    "spot": false,
    "exchange": "binance",
    "session_name": "2020-01-01_2023-12-18",
    "caches_dirpath": "/storage/tedy/passivbot/configs/live/PBSO/BT_UNIFORMISED/bt_2020-01-01_2023-12-18_1000_1/strat_1c4fcf41f6a3813cd46d5a6e27490857/binance/UNIUSDT/caches/",
    "plots_dirpath": "/storage/tedy/passivbot/configs/live/PBSO/BT_UNIFORMISED/bt_2020-01-01_2023-12-18_1000_1/strat_1c4fcf41f6a3813cd46d5a6e27490857/binance/UNIUSDT/plots/2023-12-31T100325/",
    "c_mult": 1.0,
    "hedge_mode": true,
    "inverse": false,
    "maker_fee": 0.0002,
    "min_cost": 5.0,
    "min_qty": 1.0,
    "price_step": 0.001,
    "qty_step": 1.0,
    "taker_fee": 0.0004,
    "n_parts": 0,
    "config_name": "recursive_grid_0days",
    "logging_level": 0,
    "long": {
        "auto_unstuck_delay_minutes": 0.0,
        "auto_unstuck_ema_dist": 0,
        "auto_unstuck_qty_pct": 0.0,
        "auto_unstuck_wallet_exposure_threshold": 0.0,
        "backwards_tp": false,
        "ddown_factor": 1.9429356893105973,
        "ema_span_0": 21.904429521864973,
        "ema_span_1": 28.99753464071062,
        "enabled": true,
        "initial_eprice_ema_dist": -0.0342119625599497,
        "initial_qty_pct": 0.0035095248726607943,
        "markup_range": 0.009981346443490476,
        "min_markup": 0.006702545775106026,
        "n_close_orders": 5,
        "rentry_pprice_dist": 0.008584764630856032,
        "rentry_pprice_dist_wallet_exposure_weighting": 0.330721782458209,
        "wallet_exposure_limit": 1
    },
    "short": {
        "auto_unstuck_delay_minutes": 0.0,
        "auto_unstuck_ema_dist": -0.06924659894741833,
        "auto_unstuck_qty_pct": 0.0,
        "auto_unstuck_wallet_exposure_threshold": 0.05191159266629444,
        "backwards_tp": false,
        "ddown_factor": 1.4555443282617795,
        "ema_span_0": 1116.0771199456067,
        "ema_span_1": 875.9403613954809,
        "enabled": false,
        "initial_eprice_ema_dist": -0.04591531832052814,
        "initial_qty_pct": 0.06135165253959389,
        "markup_range": 0.04876857675316166,
        "min_markup": 0.007192318046283818,
        "n_close_orders": 6,
        "rentry_pprice_dist": 0.008912756048814334,
        "rentry_pprice_dist_wallet_exposure_weighting": 15.877394666194704,
        "wallet_exposure_limit": 1
    },
    "disable_plotting": false,
    "passivbot_mode": "recursive_grid",
    "n_days": 1185.7,
    "result": {
        "adg_long": 0.0017495121684025783,
        "adg_per_exposure_long": 0.0017495121684025783,
        "adg_per_exposure_short": 0.0,
        "adg_short": 0.0,
        "adg_weighted_long": 0.00017495121684025784,
        "adg_weighted_per_exposure_long": 0.00017495121684025784,
        "adg_weighted_per_exposure_short": 0.0,
        "adg_weighted_short": 0.0,
        "avg_fills_per_day_long": 6.333989316840033,
        "avg_fills_per_day_short": 0.0,
        "closest_bkr_long": 0.962396026401189,
        "closest_bkr_short": 1.0,
        "drawdown_1pct_worst_mean_long": 0.9067612716598232,
        "drawdown_1pct_worst_mean_short": -0.0,
        "drawdown_max_long": 0.9180061744495577,
        "drawdown_max_short": -0.0,
        "eqbal_ratio_mean_long": 0.3533216890005815,
        "eqbal_ratio_mean_of_10_worst_long": 0.0836719786707754,
        "eqbal_ratio_mean_of_10_worst_short": 1.0,
        "eqbal_ratio_mean_short": 1.0,
        "eqbal_ratio_min_long": 0.08206893070687692,
        "eqbal_ratio_min_short": NaN,
        "eqbal_ratio_std_long": 0.26971641439853894,
        "eqbal_ratio_std_short": 0.0,
        "equity_balance_ratio_mean_long": 0.3533216890005815,
        "equity_balance_ratio_mean_short": 1.0,
        "equity_balance_ratio_std_long": 0.26971641439853894,
        "equity_balance_ratio_std_short": 0.0,
        "exchange": "binance",
        "exposure_ratios_mean_long": 0.9857403830977136,
        "exposure_ratios_mean_short": 0.0,
        "fee_sum_long": -320.97740752000004,
        "fee_sum_short": 0,
        "final_balance_long": 7944.865211036754,
        "final_balance_short": 1000.0,
        "final_equity_long": 1197.087592480052,
        "final_equity_short": 1000.0,
        "gain_long": 6.9448652110367535,
        "gain_short": 0.0,
        "hrs_stuck_avg_long": 0.7638567052869889,
        "hrs_stuck_avg_short": NaN,
        "hrs_stuck_max_long": 2842.4333333333334,
        "hrs_stuck_max_short": NaN,
        "loss_profit_ratio_long": 0.0,
        "loss_profit_ratio_short": 1.0,
        "loss_sum_long": 0.0,
        "loss_sum_short": 0,
        "n_closes_long": 5038,
        "n_closes_short": 0,
        "n_days": 1185.6666666666667,
        "n_entries_long": 2472,
        "n_entries_short": 0,
        "n_fills_long": 7510,
        "n_fills_short": 0,
        "n_ientries_long": 1018,
        "n_ientries_short": 0,
        "n_normal_closes_long": 5038,
        "n_normal_closes_short": 0,
        "n_rentries_long": 1454,
        "n_rentries_short": 0,
        "n_unstuck_closes_long": 0,
        "n_unstuck_closes_short": 0,
        "n_unstuck_entries_long": 0,
        "n_unstuck_entries_short": 0,
        "net_pnl_plus_fees_long": 6944.865211036716,
        "net_pnl_plus_fees_short": 0,
        "pa_distance_1pct_worst_mean_long": 9.41586009948059,
        "pa_distance_1pct_worst_mean_short": 100.0,
        "pa_distance_max_long": 10.772319295709442,
        "pa_distance_max_short": 100.0,
        "pa_distance_mean_long": 3.672919497409802,
        "pa_distance_mean_short": 100.0,
        "pa_distance_std_long": 2.776632781686218,
        "pa_distance_std_short": 1.0,
        "pnl_sum_long": 7265.842618556716,
        "pnl_sum_short": 0,
        "profit_sum_long": 7265.842618556716,
        "profit_sum_short": 0,
        "sharpe_ratio_long": 0.029401781949907856,
        "sharpe_ratio_short": 0.0,
        "starting_balance": 1000.0,
        "symbol": "UNIUSDT",
        "time_at_max_exposure_long": 0.981375408511087,
        "time_at_max_exposure_short": 0.0,
        "volume_quote_long": 3722839.2425629715,
        "volume_quote_short": 0
    }
}