{
    "market_type": "futures",
    "user": "binance_tedy",
    "symbol": "XRPUSDT",
    "latency_simulation_ms": 1000,
    "starting_balance": 1000.0,
    "start_date": "2020-01-01",
    "end_date": "2023-12-18",
    "slim_analysis": true,
    "base_dir": "/storage/tedy/passivbot/configs/live/PBSO/BT_UNIFORMISED/bt_2020-01-01_2023-12-18_1000_1/strat_0a69137d994330937f82316fda0eb74f/",
    "ohlcv": true,
    "adg_n_subdivisions": 10,
    "enable_interactive_plot": false,
    "plot_theme": "light",
    "plot_candles_interval": "1m",
    "symbols": [
        "XRPUSDT"
    ],
    "spot": false,
    "exchange": "binance",
    "session_name": "2020-01-01_2023-12-18",
    "caches_dirpath": "/storage/tedy/passivbot/configs/live/PBSO/BT_UNIFORMISED/bt_2020-01-01_2023-12-18_1000_1/strat_0a69137d994330937f82316fda0eb74f/binance/XRPUSDT/caches/",
    "plots_dirpath": "/storage/tedy/passivbot/configs/live/PBSO/BT_UNIFORMISED/bt_2020-01-01_2023-12-18_1000_1/strat_0a69137d994330937f82316fda0eb74f/binance/XRPUSDT/plots/2023-12-29T104929/",
    "c_mult": 1.0,
    "hedge_mode": true,
    "inverse": false,
    "maker_fee": 0.0002,
    "min_cost": 5.0,
    "min_qty": 0.1,
    "price_step": 0.0001,
    "qty_step": 0.1,
    "taker_fee": 0.0004,
    "n_parts": 0,
    "config_name": "recursive_grid_0days",
    "logging_level": 0,
    "long": {
        "auto_unstuck_delay_minutes": 0.0,
        "auto_unstuck_ema_dist": 0,
        "auto_unstuck_qty_pct": 0.0,
        "auto_unstuck_wallet_exposure_threshold": 0.0,
        "backwards_tp": true,
        "ddown_factor": 1.3897977397660237,
        "ema_span_0": 434.7490060702662,
        "ema_span_1": 277.4309414936194,
        "enabled": true,
        "initial_eprice_ema_dist": 0.007960347927775276,
        "initial_qty_pct": 0.01779747248236638,
        "markup_range": 0.001409094423771131,
        "min_markup": 0.0036314148053348183,
        "n_close_orders": 2,
        "rentry_pprice_dist": 0.027708406271782015,
        "rentry_pprice_dist_wallet_exposure_weighting": 4.4732924923321615,
        "wallet_exposure_limit": 1
    },
    "short": {
        "auto_unstuck_delay_minutes": 0.0,
        "auto_unstuck_ema_dist": -0.04339890714563181,
        "auto_unstuck_qty_pct": 0.0,
        "auto_unstuck_wallet_exposure_threshold": 0.03221172766988559,
        "backwards_tp": true,
        "ddown_factor": 0.1782504246567218,
        "ema_span_0": 425.6713636313203,
        "ema_span_1": 1009.3645830367701,
        "enabled": false,
        "initial_eprice_ema_dist": -0.027962559122396938,
        "initial_qty_pct": 0.09216436324867662,
        "markup_range": 0.03533181313986953,
        "min_markup": 0.00539393120321063,
        "n_close_orders": 3,
        "rentry_pprice_dist": 0.02764982398821787,
        "rentry_pprice_dist_wallet_exposure_weighting": 6.859663884297291,
        "wallet_exposure_limit": 1
    },
    "disable_plotting": false,
    "passivbot_mode": "recursive_grid",
    "n_days": 1441.7,
    "result": {
        "adg_long": 0.0013576563644708273,
        "adg_per_exposure_long": 0.0013576563644708273,
        "adg_per_exposure_short": 0.0,
        "adg_short": 0.0,
        "adg_weighted_long": 0.0005518461648308826,
        "adg_weighted_per_exposure_long": 0.0005518461648308826,
        "adg_weighted_per_exposure_short": 0.0,
        "adg_weighted_short": 0.0,
        "avg_fills_per_day_long": 12.345790340761294,
        "avg_fills_per_day_short": 0.0,
        "closest_bkr_long": 0.9998347806334726,
        "closest_bkr_short": 1.0,
        "drawdown_1pct_worst_mean_long": 0.20165921121412472,
        "drawdown_1pct_worst_mean_short": -0.0,
        "drawdown_max_long": 0.3773251184235972,
        "drawdown_max_short": -0.0,
        "eqbal_ratio_mean_long": 0.9970953725225911,
        "eqbal_ratio_mean_of_10_worst_long": 0.6682215774101297,
        "eqbal_ratio_mean_of_10_worst_short": 1.0,
        "eqbal_ratio_mean_short": 1.0,
        "eqbal_ratio_min_long": 0.6227994286057399,
        "eqbal_ratio_min_short": NaN,
        "eqbal_ratio_std_long": 0.022517459543348616,
        "eqbal_ratio_std_short": 0.0,
        "equity_balance_ratio_mean_long": 0.9970953725225911,
        "equity_balance_ratio_mean_short": 1.0,
        "equity_balance_ratio_std_long": 0.022517459543348616,
        "equity_balance_ratio_std_short": 0.0,
        "exchange": "binance",
        "exposure_ratios_mean_long": 0.03101146466751074,
        "exposure_ratios_mean_short": 0.0,
        "fee_sum_long": -374.387953278,
        "fee_sum_short": 0,
        "final_balance_long": 7070.307226722,
        "final_balance_short": 1000.0,
        "final_equity_long": 7067.035816722,
        "final_equity_short": 1000.0,
        "gain_long": 6.070307226722001,
        "gain_short": 0.0,
        "hrs_stuck_avg_long": 1.9397257964825532,
        "hrs_stuck_avg_short": NaN,
        "hrs_stuck_max_long": 349.35,
        "hrs_stuck_max_short": NaN,
        "loss_profit_ratio_long": 0.0,
        "loss_profit_ratio_short": 1.0,
        "loss_sum_long": 0.0,
        "loss_sum_short": 0,
        "n_closes_long": 7846,
        "n_closes_short": 0,
        "n_days": 1441.625,
        "n_entries_long": 9952,
        "n_entries_short": 0,
        "n_fills_long": 17798,
        "n_fills_short": 0,
        "n_ientries_long": 7754,
        "n_ientries_short": 0,
        "n_normal_closes_long": 7846,
        "n_normal_closes_short": 0,
        "n_rentries_long": 2198,
        "n_rentries_short": 0,
        "n_unstuck_closes_long": 0,
        "n_unstuck_closes_short": 0,
        "n_unstuck_entries_long": 0,
        "n_unstuck_entries_short": 0,
        "net_pnl_plus_fees_long": 6070.307226721996,
        "net_pnl_plus_fees_short": 0,
        "pa_distance_1pct_worst_mean_long": 0.26097943833083165,
        "pa_distance_1pct_worst_mean_short": 100.0,
        "pa_distance_max_long": 0.6055592627168551,
        "pa_distance_max_short": 100.0,
        "pa_distance_mean_long": 0.017157657478216272,
        "pa_distance_mean_short": 100.0,
        "pa_distance_std_long": 0.04632316582446045,
        "pa_distance_std_short": 1.0,
        "pnl_sum_long": 6444.695179999996,
        "pnl_sum_short": 0,
        "profit_sum_long": 6444.695179999996,
        "profit_sum_short": 0,
        "sharpe_ratio_long": 0.09271973695621542,
        "sharpe_ratio_short": 0.0,
        "starting_balance": 1000.0,
        "symbol": "XRPUSDT",
        "time_at_max_exposure_long": 0.01705202312138728,
        "time_at_max_exposure_short": 0.0,
        "volume_quote_long": 1406995.6263643126,
        "volume_quote_short": 0
    }
}